{"data":{"metrics":[{"units":"min","name":"apple_exercise_time","data":[{"source":"Anthony’s Apple Watch","date":"2026-06-23 14:43:09 +1000","qty":4}]},{"name":"apple_stand_time","units":"min","data":[{"source":"Anthony’s Apple Watch","date":"2026-06-23 14:43:09 +1000","qty":7}]},{"units":"kJ","data":[{"date":"2026-06-23 14:43:09 +1000","source":"Anthony’s Apple Watch","qty":187.69842400000002}],"name":"active_energy"},{"name":"apple_stand_hour","data":[{"source":"","date":"2026-06-23 00:00:00 +1000","qty":1}],"units":"count"},{"name":"heart_rate","units":"count/min","data":[{"Min":54,"Avg":61.69667798538291,"Max":99,"date":"2026-06-23 14:43:09 +1000","source":"Anthony’s Apple Watch"}]},{"name":"basal_energy_burned","data":[{"date":"2026-06-23 14:43:09 +1000","qty":469.02221599999996,"source":"Anthony’s Apple Watch"}],"units":"kJ"},{"units":"ms","data":[{"source":"Anthony’s Apple Watch","date":"2026-06-23 00:00:00 +1000","qty":31.44847231278603}],"name":"heart_rate_variability"},{"units":"kcal/hr·kg","name":"physical_effort","data":[{"date":"2026-06-23 00:00:00 +1000","source":"Anthony’s Apple Watch","qty":3.669696977644256}]},{"units":"count","data":[{"source":"Anthony’s Apple Watch|Tony Baba iPhone ","qty":200.63101851912518,"date":"2026-06-23 14:43:09 +1000"}],"name":"step_count"},{"data":[{"date":"2026-06-23 00:00:00 +1000","qty":0.36959075927734375,"source":"Anthony’s Apple Watch"}],"units":"m/s","name":"stair_speed_down"},{"name":"walking_running_distance","data":[{"source":"Anthony’s Apple Watch|Tony Baba iPhone ","qty":0.40560965118168657,"date":"2026-06-23 14:43:09 +1000"}],"units":"km"},{"data":[{"date":"2026-06-23 00:00:00 +1000","qty":3.888,"source":"Tony Baba iPhone"}],"name":"walking_speed","units":"km/hr"},{"name":"walking_step_length","units":"cm","data":[{"date":"2026-06-23 00:00:00 +1000","qty":63,"source":"Tony Baba iPhone"}]}]}}