{"data":{"metrics":[{"units":"kJ","data":[{"date":"2026-06-25 00:00:00 +1000","qty":2749.8586880000325,"source":"Anthony’s Apple Watch"},{"source":"Anthony’s Apple Watch","date":"2026-06-26 00:00:00 +1000","qty":1591.1584639999994},{"qty":6510.082248000009,"date":"2026-06-27 00:00:00 +1000","source":"Anthony’s Apple Watch"},{"qty":1127.424823999999,"date":"2026-06-28 00:00:00 +1000","source":"Anthony’s Apple Watch"},{"qty":2657.199824,"date":"2026-06-29 00:00:00 +1000","source":"Anthony’s Apple Watch"},{"qty":3006.1119520000366,"source":"Anthony’s Apple Watch","date":"2026-06-30 00:00:00 +1000"},{"qty":1188.2476320000007,"source":"Anthony’s Apple Watch","date":"2026-07-01 00:00:00 +1000"}],"name":"active_energy"},{"units":"count/min","data":[{"Avg":59.44451571114285,"source":"Anthony’s Apple Watch","Min":41,"date":"2026-06-25 00:00:00 +1000","Max":116},{"source":"Anthony’s Apple Watch","Min":41.96511459350586,"Avg":52.43639260191423,"date":"2026-06-26 00:00:00 +1000","Max":101},{"Avg":81.0718194093005,"Max":164,"date":"2026-06-27 00:00:00 +1000","Min":42,"source":"Bluetooth Device|Anthony’s Apple Watch"},{"source":"Bluetooth Device|Anthony’s Apple Watch","Min":47,"date":"2026-06-28 00:00:00 +1000","Avg":59.06891795206994,"Max":104},{"Min":41,"source":"Bluetooth Device|Anthony’s Apple Watch","Max":152,"Avg":63.59533671132686,"date":"2026-06-29 00:00:00 +1000"},{"Min":42,"source":"Bluetooth Device|Anthony’s Apple Watch","Avg":65.17768196729992,"Max":130,"date":"2026-06-30 00:00:00 +1000"},{"Min":46,"Avg":62.88279951604993,"date":"2026-07-01 00:00:00 +1000","source":"Bluetooth Device|Anthony’s Apple Watch","Max":105}],"name":"heart_rate"},{"name":"apple_exercise_time","data":[{"date":"2026-06-25 00:00:00 +1000","qty":85,"source":"Anthony’s Apple Watch"},{"date":"2026-06-26 00:00:00 +1000","qty":15,"source":"Anthony’s Apple Watch"},{"date":"2026-06-27 00:00:00 +1000","qty":98,"source":"Anthony’s Apple Watch"},{"date":"2026-06-28 00:00:00 +1000","source":"Anthony’s Apple Watch","qty":3},{"qty":31,"date":"2026-06-29 00:00:00 +1000","source":"Anthony’s Apple Watch"},{"date":"2026-06-30 00:00:00 +1000","source":"Anthony’s Apple Watch","qty":79},{"source":"Anthony’s Apple Watch","date":"2026-07-01 00:00:00 +1000","qty":13}],"units":"min"},{"name":"blood_oxygen_saturation","data":[{"source":"Anthony’s Apple Watch","date":"2026-06-25 00:00:00 +1000","qty":96.42857142857143},{"qty":95.84210526315789,"date":"2026-06-26 00:00:00 +1000","source":"Anthony’s Apple Watch"},{"source":"Anthony’s Apple Watch","date":"2026-06-27 00:00:00 +1000","qty":96.18181818181819},{"date":"2026-06-28 00:00:00 +1000","source":"Anthony’s Apple Watch","qty":95.63636363636364},{"date":"2026-06-29 00:00:00 +1000","qty":96.83333333333333,"source":"Anthony’s Apple Watch"},{"source":"Anthony’s Apple Watch","qty":96.76923076923077,"date":"2026-06-30 00:00:00 +1000"},{"source":"Anthony’s Apple Watch","date":"2026-07-01 00:00:00 +1000","qty":96.26315789473684}],"units":"%"},{"name":"walking_running_distance","data":[{"date":"2026-06-25 00:00:00 +1000","source":"Anthony’s Apple Watch|Tony Baba iPhone ","qty":6.5808514386909085},{"date":"2026-06-26 00:00:00 +1000","source":"Anthony’s Apple Watch|Tony Baba iPhone ","qty":4.405128285089373},{"date":"2026-06-27 00:00:00 +1000","source":"Anthony’s Apple Watch|Tony Baba iPhone ","qty":19.440056396577855},{"qty":2.416113573941402,"source":"Anthony’s Apple Watch|Tony Baba iPhone ","date":"2026-06-28 00:00:00 +1000"},{"source":"Anthony’s Apple Watch|Tony Baba iPhone ","date":"2026-06-29 00:00:00 +1000","qty":7.551787830942427},{"date":"2026-06-30 00:00:00 +1000","qty":6.788287924466216,"source":"Anthony’s Apple Watch|Tony Baba iPhone "},{"qty":3.0829318516237856,"source":"Anthony’s Apple Watch|Tony Baba iPhone ","date":"2026-07-01 00:00:00 +1000"}],"units":"km"},{"units":"count/min","data":[{"date":"2026-06-25 00:00:00 +1000","source":"Anthony’s Apple Watch","qty":13.875},{"qty":14.092857142857143,"source":"Anthony’s Apple Watch","date":"2026-06-26 00:00:00 +1000"},{"qty":13.55,"source":"Anthony’s Apple Watch","date":"2026-06-27 00:00:00 +1000"},{"qty":14.276785714285714,"date":"2026-06-28 00:00:00 +1000","source":"Anthony’s Apple Watch"},{"qty":13.735849056603774,"source":"Anthony’s Apple Watch","date":"2026-06-29 00:00:00 +1000"},{"date":"2026-06-30 00:00:00 +1000","source":"Anthony’s Apple Watch","qty":14.011627906976743},{"source":"Anthony’s Apple Watch","date":"2026-07-01 00:00:00 +1000","qty":16.061855670103093}],"name":"respiratory_rate"},{"name":"apple_sleeping_wrist_temperature","units":"degC","data":[{"date":"2026-06-25 00:00:00 +1000","source":"Anthony’s Apple Watch","qty":35.79554748535156},{"source":"Anthony’s Apple Watch","date":"2026-06-26 00:00:00 +1000","qty":35.67293167114258},{"qty":35.143463134765625,"date":"2026-06-28 00:00:00 +1000","source":"Anthony’s Apple Watch"},{"source":"Anthony’s Apple Watch","date":"2026-06-29 00:00:00 +1000","qty":35.28672409057617},{"qty":36.38945007324219,"date":"2026-06-30 00:00:00 +1000","source":"Anthony’s Apple Watch"},{"date":"2026-07-01 00:00:00 +1000","source":"Anthony’s Apple Watch","qty":35.33905029296875}]},{"data":[{"source":"Anthony’s Apple Watch","date":"2026-06-25 00:00:00 +1000","qty":52.1655212191315},{"source":"Anthony’s Apple Watch","date":"2026-06-26 00:00:00 +1000","qty":55.1402985155534},{"date":"2026-06-27 00:00:00 +1000","qty":55.74245491503757,"source":"Anthony’s Apple Watch"},{"source":"Anthony’s Apple Watch","qty":49.65387805452994,"date":"2026-06-28 00:00:00 +1000"},{"source":"Anthony’s Apple Watch","date":"2026-06-29 00:00:00 +1000","qty":54.195169090250786},{"source":"Anthony’s Apple Watch","qty":49.218083408340384,"date":"2026-06-30 00:00:00 +1000"},{"source":"Anthony’s Apple Watch","qty":39.03271738727338,"date":"2026-07-01 00:00:00 +1000"}],"units":"ms","name":"heart_rate_variability"},{"data":[{"date":"2026-06-27 00:00:00 +1000","qty":59.8,"source":"Anthony’s Apple Watch"},{"date":"2026-06-29 00:00:00 +1000","qty":59.85,"source":"Anthony’s Apple Watch"}],"name":"vo2_max","units":"ml/(kg·min)"},{"name":"resting_heart_rate","units":"count/min","data":[{"source":"Anthony’s Apple Watch","date":"2026-06-25 00:00:00 +1000","qty":51},{"source":"Anthony’s Apple Watch","qty":50,"date":"2026-06-26 00:00:00 +1000"},{"date":"2026-06-27 00:00:00 +1000","qty":54,"source":"Anthony’s Apple Watch"},{"qty":56,"source":"Anthony’s Apple Watch","date":"2026-06-28 00:00:00 +1000"},{"date":"2026-06-29 00:00:00 +1000","qty":52,"source":"Anthony’s Apple Watch"},{"date":"2026-06-30 00:00:00 +1000","qty":52,"source":"Anthony’s Apple Watch"}]},{"name":"sleep_analysis","data":[{"sleepEnd":"2026-06-25 06:07:21 +1000","inBedStart":"2026-06-24 22:11:35 +1000","inBedEnd":"2026-06-25 06:07:21 +1000","awake":0.09963491416639753,"sleepStart":"2026-06-24 22:11:35 +1000","source":"Anthony’s Apple Watch","rem":1.735332865284549,"date":"2026-06-25 00:00:00 +1000","asleep":0,"core":4.724340198073122,"inBed":0,"totalSleep":7.829578787386417,"deep":1.3699057240287462},{"inBedStart":"2026-06-25 21:59:48 +1000","deep":1.0378494359718429,"inBedEnd":"2026-06-26 07:57:37 +1000","core":4.41715993212329,"asleep":0,"inBed":0,"rem":2.001095212664869,"date":"2026-06-26 00:00:00 +1000","sleepEnd":"2026-06-26 07:57:37 +1000","totalSleep":7.456104580760003,"awake":2.507358014451133,"source":"Anthony’s Apple Watch","sleepStart":"2026-06-25 21:59:48 +1000"},{"inBedEnd":"2026-06-27 06:42:22 +1000","inBed":0,"totalSleep":7.05728497972091,"deep":0.6476360205809275,"source":"Anthony’s Apple Watch","sleepEnd":"2026-06-27 06:42:22 +1000","core":4.956613880693912,"date":"2026-06-27 00:00:00 +1000","asleep":0,"awake":0.27400116003221936,"rem":1.4530350784460704,"sleepStart":"2026-06-26 23:22:30 +1000","inBedStart":"2026-06-26 23:22:30 +1000"},{"deep":0.9880560444792111,"source":"Anthony’s Apple Watch","core":5.139590775701735,"inBed":0,"sleepStart":"2026-06-28 01:02:29 +1000","date":"2026-06-28 00:00:00 +1000","sleepEnd":"2026-06-28 09:25:09 +1000","totalSleep":8.34445997685194,"inBedStart":"2026-06-28 01:02:29 +1000","rem":2.2168131566709945,"awake":0.033209249575932825,"inBedEnd":"2026-06-28 09:25:09 +1000","asleep":0},{"date":"2026-06-29 00:00:00 +1000","deep":1.0377795158161056,"inBedEnd":"2026-06-29 06:42:55 +1000","sleepEnd":"2026-06-29 06:42:55 +1000","awake":0.14944906622171403,"inBed":0,"rem":1.668875828617149,"sleepStart":"2026-06-29 00:11:21 +1000","totalSleep":6.37649971432156,"source":"Anthony’s Apple Watch","asleep":0,"inBedStart":"2026-06-29 00:11:21 +1000","core":3.669844369888305},{"rem":1.7685016534725826,"totalSleep":6.8163768783211705,"inBed":0,"sleepEnd":"2026-06-30 06:08:58 +1000","date":"2026-06-30 00:00:00 +1000","sleepStart":"2026-06-29 23:11:01 +1000","asleep":0,"inBedEnd":"2026-06-30 06:08:58 +1000","source":"Anthony’s Apple Watch","deep":0.8883098412553468,"awake":0.14944426543182796,"inBedStart":"2026-06-29 23:11:01 +1000","core":4.159565383593241},{"sleepEnd":"2026-07-01 06:12:39 +1000","core":4.276021442479557,"source":"Anthony’s Apple Watch","deep":0.41519118862019644,"sleepStart":"2026-07-01 00:30:24 +1000","inBed":0,"date":"2026-07-01 00:00:00 +1000","inBedEnd":"2026-07-01 06:12:39 +1000","asleep":0,"totalSleep":4.732728093862534,"rem":0.04151546276277966,"inBedStart":"2026-07-01 00:30:24 +1000","awake":0.9714249758256805}],"units":"hr"},{"name":"running_ground_contact_time","units":"ms","data":[{"source":"Anthony’s Apple Watch","date":"2026-06-27 00:00:00 +1000","qty":222.49045521292217},{"date":"2026-06-29 00:00:00 +1000","source":"Anthony’s Apple Watch","qty":231.62886597938143}]},{"data":[{"qty":1.2436046511627954,"source":"Anthony’s Apple Watch","date":"2026-06-27 00:00:00 +1000"},{"date":"2026-06-29 00:00:00 +1000","qty":1.1652559726962464,"source":"Anthony’s Apple Watch"}],"name":"running_stride_length","units":"m"},{"data":[{"date":"2026-06-27 00:00:00 +1000","source":"Anthony’s Apple Watch","qty":12.195417970846442},{"source":"Anthony’s Apple Watch","date":"2026-06-29 00:00:00 +1000","qty":11.330555345128927}],"name":"running_speed","units":"km/hr"},{"data":[{"date":"2026-06-27 00:00:00 +1000","qty":10.105643994211288,"source":"Anthony’s Apple Watch"},{"date":"2026-06-29 00:00:00 +1000","qty":9.335034013605444,"source":"Anthony’s Apple Watch"}],"name":"running_vertical_oscillation","units":"cm"},{"data":[{"source":"Anthony’s Apple Watch","qty":269.51897905759165,"date":"2026-06-27 00:00:00 +1000"},{"source":"Anthony’s Apple Watch","date":"2026-06-29 00:00:00 +1000","qty":249.53301886792454}],"name":"running_power","units":"W"}]}}